{"cameraMode":{"drawMode":0,"name":"Shaded","section":"Shading Mode"},"sceneLighting":false,"audioPlay":false,"sceneViewState":{"m_AlwaysRefresh":false,"showFog":true,"showSkybox":false,"showFlares":true,"showImageEffects":true,"showParticleSystems":true,"showVisualEffectGraphs":true,"m_FxEnabled":true},"in2DMode":false,"pivot":{"x":14.154806137084961,"y":-5.678298473358154,"z":11.174980163574219},"rotation":{"x":0.1638597995042801,"y":0.650299608707428,"z":-0.1462077796459198,"w":0.7272844314575195},"size":12.323822021484375,"orthographic":false}